README.txt
setup.cfg
setup.py
dj_cmdbuild.egg-info/PKG-INFO
dj_cmdbuild.egg-info/SOURCES.txt
dj_cmdbuild.egg-info/dependency_links.txt
dj_cmdbuild.egg-info/top_level.txt
django_cmdbuild/__init__.py
django_cmdbuild/inspect.py
django_cmdbuild/models/__init__.py
django_cmdbuild/models/activity.py
django_cmdbuild/models/expander.py
django_cmdbuild/models/helpers.py
django_cmdbuild/models/introspection_common.py
django_cmdbuild/models/querysets.py
django_cmdbuild/models/related.py
django_cmdbuild/remoteapi/__init__.py
django_cmdbuild/remoteapi/http.py
django_cmdbuild/serializer/__init__.py
django_cmdbuild/serializer/jsonconverter.py
