Metadata-Version: 1.0
Name: dj-cmdbuild
Version: 0.1dev-r23
Summary: Tools for interfacing Django with CMDBuild databases
Home-page: http://code.google.com/p/dj-cmdbuild
Author: Emanuele Pucciarelli
Author-email: ep@acm.org
License: GPL
Keywords: django cmdbuild
Platform: UNKNOWN
